farm_ng_core_pybind.cpython-311-darwin.so
farm_ng_core-2.3.1.dist-info/RECORD
farm_ng_core-2.3.1.dist-info/LICENSE
farm_ng_core-2.3.1.dist-info/WHEEL
farm_ng_core-2.3.1.dist-info/top_level.txt
farm_ng_core-2.3.1.dist-info/METADATA
farm_ng/core/events_file_reader.py
farm_ng/core/event_client_manager.py
farm_ng/core/pose_tree.py
farm_ng/core/event_service_pb2_grpc.py
farm_ng/core/timestamp.proto
farm_ng/core/event_pb2.pyi
farm_ng/core/recorder_pb2_grpc.py
farm_ng/core/std.proto
farm_ng/core/timestamp_pb2.pyi
farm_ng/core/event_service.py
farm_ng/core/sensor_pb2.pyi
farm_ng/core/uri_pb2.py
farm_ng/core/pose_pb2.pyi
farm_ng/core/geometry_pb2.pyi
farm_ng/core/color_pb2.pyi
farm_ng/core/events_file_writer.py
farm_ng/core/lie_pb2.pyi
farm_ng/core/examples_pb2.py
farm_ng/core/recorder_pb2.py
farm_ng/core/examples_pb2.pyi
farm_ng/core/uri.proto
farm_ng/core/calculus_pb2_grpc.py
farm_ng/core/examples_pb2_grpc.py
farm_ng/core/event_pb2_grpc.py
farm_ng/core/event_service_recorder.py
farm_ng/core/uri_pb2.pyi
farm_ng/core/__init__.py
farm_ng/core/image_pb2_grpc.py
farm_ng/core/event_service_pb2.pyi
farm_ng/core/std_pb2.py
farm_ng/core/color.proto
farm_ng/core/recorder.proto
farm_ng/core/color_pb2_grpc.py
farm_ng/core/sensor_pb2.py
farm_ng/core/sensor_pb2_grpc.py
farm_ng/core/lie_pb2_grpc.py
farm_ng/core/geometry.proto
farm_ng/core/event_service_metrics.py
farm_ng/core/calculus_pb2.pyi
farm_ng/core/timestamp_pb2_grpc.py
farm_ng/core/linalg_pb2_grpc.py
farm_ng/core/uri.py
farm_ng/core/stamp.py
farm_ng/core/std_pb2_grpc.py
farm_ng/core/event.proto
farm_ng/core/pose_pb2.py
farm_ng/core/event_pb2.py
farm_ng/core/pose_pb2_grpc.py
farm_ng/core/event_service_tool.py
farm_ng/core/linalg_pb2.py
farm_ng/core/event_client.py
farm_ng/core/sensor.proto
farm_ng/core/linalg_pb2.pyi
farm_ng/core/uri_pb2_grpc.py
farm_ng/core/examples.proto
farm_ng/core/event_service_pb2.py
farm_ng/core/calculus_pb2.py
farm_ng/core/calculus.proto
farm_ng/core/image_pb2.pyi
farm_ng/core/geometry_pb2.py
farm_ng/core/lie.proto
farm_ng/core/image_pb2.py
farm_ng/core/linalg.proto
farm_ng/core/std_pb2.pyi
farm_ng/core/timestamp_pb2.py
