Metadata-Version: 2.1
Name: farm_ng_core
Version: 2.3.1
Home-page: https://github.com/farm-ng/farm-ng-core
Download-URL: https://github.com/farm-ng/farm-ng-core
Author: Farm-ng Inc.
Author-email: info@farm-ng.com
Keywords: robotics,open-source
Classifier: Development Status :: 4 - Beta
Classifier: Intended Audience :: Developers
Classifier: License :: OSI Approved :: Apache Software License
Classifier: Operating System :: OS Independent
Classifier: Programming Language :: Python :: 3
Classifier: Topic :: Software Development
Classifier: Framework :: Robot Framework
Requires-Python: >=3.8
License-File: LICENSE
Requires-Dist: farm_ng_package
Requires-Dist: protobuf
Requires-Dist: grpcio
Requires-Dist: psutil
Requires-Dist: numpy
Provides-Extra: dev
Requires-Dist: pytest; extra == "dev"
Requires-Dist: pytest-mypy; extra == "dev"
Requires-Dist: pre-commit; extra == "dev"
Requires-Dist: mypy; extra == "dev"
Requires-Dist: types-protobuf; extra == "dev"
Requires-Dist: pylint; extra == "dev"
Requires-Dist: grpcio-tools; extra == "dev"
Requires-Dist: mypy-protobuf; extra == "dev"
Requires-Dist: pylint-protobuf; extra == "dev"
Requires-Dist: anyio; extra == "dev"
